{
"medicamentos":[
    {
      "id": 1,
      "nomeMedicamento": "Paracetamol",
      "quantidade": 100,
      "dosagem": "500mg",
      "formaFarmaceutica": "Comprimido",
      "categoria": "Analgésicos",
      "tarja": "Vermelha",
      "lote": "L001"
    },
    {
      "id": 2,
      "nomeMedicamento": "Ibuprofeno",
      "quantidade": 150,
      "dosagem": "200mg",
      "formaFarmaceutica": "Cápsula",
      "categoria": "Anti-inflamatórios",
      "tarja": "Vermelha",
      "lote": "L002"
    }
  ],
  "lotes": [
    {
      "id": 1,
      "quantidadeEstoque": 500,
      "fornecedor": "Farmacêutica A",
      "dataFabricacao": "2024-01-10",
      "dataValidade": "2025-01-10"
    },
    {
      "id": 2,
      "quantidadeEstoque": 600,
      "fornecedor": "Farmacêutica B",
      "dataFabricacao": "2024-03-15",
      "dataValidade": "2025-03-15"
    }
  ],
  "categoriaMedicamentos": [
    {
      "id": 1,
      "nomeCategoria": "Analgésicos",
      "descricao": "Medicamentos usados para aliviar dores leves e moderadas."
    },
    {
      "id": 2,
      "nomeCategoria": "Anti-inflamatórios",
      "descricao": "Medicamentos que reduzem a inflamação e podem aliviar dor e febre."
    }
  ],
    "funcionarios": [
    {
      "id": 1,
      "nomeFuncionario": "João da Silva",
      "cpf": "123.456.789-00",
      "dataNascimento": "1990-05-15",
      "email": "joao.silva@example.com",
      "logradouro": "Rua das Flores",
      "numero": 123,
      "complemento": "Apto 101",
      "bairro": "Centro",
      "cidade": "São Paulo",
      "estado": "SP",
      "cep": "01000-000"
    }
    ],
  {
  "pacientes": [
    {
      "id": 1,
      "nomePaciente": "Maria Oliveira",
      "cpf": "123.456.789-00",
      "dataNascimento": "1985-03-25",
      "genero": "Feminino",
      "carteirinhaSUS": "123456789012345",
      "email": "maria.oliveira@example.com",
      "telefoneCelular": "(11) 91234-5678",
      "contatoEmergencia": "(11) 99876-5432",
      "profissao": "Professora",
      "religiao": "Católica",
      "logradouro": "Rua das Palmeiras",
      "numero": 45,
      "complemento": "Casa",
      "bairro": "Jardim das Acácias",
      "cidade": "Rio de Janeiro",
      "estado": "RJ",
      "cep": "20000-000"
    }
  ]
}
